setup.cfg
setup.py
noorm/__init__.py
noorm/noorm.py
noorm/table.py
noorm/version.py
noorm.egg-info/PKG-INFO
noorm.egg-info/SOURCES.txt
noorm.egg-info/dependency_links.txt
noorm.egg-info/not-zip-safe
noorm.egg-info/top_level.txt
noorm/tests/__init__.py
noorm/tests/test_noorm.py