Metadata-Version: 1.1
Name: noorm
Version: 0.1.0
Summary: Easy pythonic access to SQLite Databases. (Not an ORM)
Home-page: http://github.com/phoglx/noorm
Author: Benjamin Borchert
Author-email: benjamin.borchert@gmail.com
License: Apache
Keywords: NoORM sqlite3
Platform: UNKNOWN
Classifier: Development Status :: 4 - Beta
Classifier: License :: OSI Approved :: Apache Software License
Classifier: Topic :: Utilities
Classifier: Programming Language :: Python
Classifier: Programming Language :: Python :: 2
Classifier: Programming Language :: Python :: 2.7
